{
    "default_filament_colour": [
        "#FF208A"
    ],
    "filament_cost": [
        "30"
    ],
    "filament_density": [
        "1.24"
    ],
    "filament_max_volumetric_speed": [
        "8"
    ],
    "filament_retraction_length": [
        "0.6"
    ],
    "filament_settings_id": [
        "PLA Eryone Tricolor Silk - OAB 23.08.30"
    ],
    "filament_start_gcode": [
        "; chamber fan speed 70% for PLA. Increase to S255 if you run your \n; printer in a hot environment.\nM106 P3 S175"
    ],
    "filament_vendor": [
        "Eryone"
    ],
    "from": "User",
    "hot_plate_temp": [
        "60"
    ],
    "hot_plate_temp_initial_layer": [
        "60"
    ],
    "inherits": "Bambu PLA Basic @BBL X1C",
    "name": "Eryone PLASilk Tricolor",
    "nozzle_temperature": [
        "230"
    ],
    "nozzle_temperature_initial_layer": [
        "230"
    ],
    "slow_down_layer_time": [
        "2"
    ],
    "temperature_vitrification": [
        "60"
    ],
    "textured_plate_temp": [
        "60"
    ],
    "textured_plate_temp_initial_layer": [
        "60"
    ],
    "version": "1.4.1.1"
}
