{
    "default_filament_colour": [
        "#FF0000"
    ],
    "filament_flow_ratio": [
        "1.118"
    ],
    "filament_settings_id": [
        "FormFutura ABS (TitanX) Red"
    ],
    "filament_vendor": [
        "FormFutura"
    ],
    "from": "User",
    "inherits": "Generic ABS",
    "name": "FormFutura ABS (TitanX) Red",
    "nozzle_temperature": [
        "255"
    ],
    "nozzle_temperature_initial_layer": [
        "255"
    ],
    "nozzle_temperature_range_high": [
        "260"
    ],
    "version": "1.7.0.12"
}
